{"nodes": [{"id": "c_users_vjtyl_downloads_spanx_extracted_spanx_lib_features_profile_tab_ui_profile_tab_dart", "label": "profile_tab.dart", "file_type": "code", "source_file": "features/profile_tab/ui/profile_tab.dart", "source_location": null}, {"id": "ui_profile_tab_profiletabpage", "label": "ProfileTabPage", "file_type": "code", "source_file": "features/profile_tab/ui/profile_tab.dart", "source_location": null}, {"id": "statelesswidget", "label": "StatelessWidget", "file_type": "code", "source_file": null, "source_location": null}, {"id": "ui_profile_tab_herostat", "label": "_HeroStat", "file_type": "code", "source_file": "features/profile_tab/ui/profile_tab.dart", "source_location": null}, {"id": "ui_profile_tab_statchip", "label": "_StatChip", "file_type": "code", "source_file": "features/profile_tab/ui/profile_tab.dart", "source_location": null}, {"id": "ui_profile_tab_menuitem", "label": "_MenuItem", "file_type": "code", "source_file": "features/profile_tab/ui/profile_tab.dart", "source_location": null}, {"id": "ui_profile_tab_kred", "label": "_kRed", "file_type": "code", "source_file": "features/profile_tab/ui/profile_tab.dart", "source_location": null}, {"id": "ui_profile_tab_kreddk", "label": "_kRedDk", "file_type": "code", "source_file": "features/profile_tab/ui/profile_tab.dart", "source_location": null}, {"id": "ui_profile_tab_kbg", "label": "_kBg", "file_type": "code", "source_file": "features/profile_tab/ui/profile_tab.dart", "source_location": null}, {"id": "ui_profile_tab_kcard", "label": "_kCard", "file_type": "code", "source_file": "features/profile_tab/ui/profile_tab.dart", "source_location": null}, {"id": "ui_profile_tab_ktext", "label": "_kText", "file_type": "code", "source_file": "features/profile_tab/ui/profile_tab.dart", "source_location": null}, {"id": "ui_profile_tab_kmuted", "label": "_kMuted", "file_type": "code", "source_file": "features/profile_tab/ui/profile_tab.dart", "source_location": null}, {"id": "ui_profile_tab_controller", "label": "controller", "file_type": "code", "source_file": "features/profile_tab/ui/profile_tab.dart", "source_location": null}, {"id": "ui_profile_tab_userinfo", "label": "userInfo", "file_type": "code", "source_file": "features/profile_tab/ui/profile_tab.dart", "source_location": null}, {"id": "ui_profile_tab_achievements", "label": "achievements", "file_type": "code", "source_file": "features/profile_tab/ui/profile_tab.dart", "source_location": null}, {"id": "ui_profile_tab_count", "label": "count", "file_type": "code", "source_file": "features/profile_tab/ui/profile_tab.dart", "source_location": null}, {"id": "ui_profile_tab_label", "label": "label", "file_type": "code", "source_file": "features/profile_tab/ui/profile_tab.dart", "source_location": null}, {"id": "ui_profile_tab_icon", "label": "icon", "file_type": "code", "source_file": "features/profile_tab/ui/profile_tab.dart", "source_location": null}, {"id": "icondata", "label": "IconData", "file_type": "code", "source_file": null, "source_location": null}, {"id": "ui_profile_tab_value", "label": "value", "file_type": "code", "source_file": "features/profile_tab/ui/profile_tab.dart", "source_location": null}, {"id": "ui_profile_tab_color", "label": "color", "file_type": "code", "source_file": "features/profile_tab/ui/profile_tab.dart", "source_location": null}, {"id": "color", "label": "Color", "file_type": "code", "source_file": null, "source_location": null}, {"id": "ui_profile_tab_item", "label": "item", "file_type": "code", "source_file": "features/profile_tab/ui/profile_tab.dart", "source_location": null}, {"id": "profilemenuitem", "label": "ProfileMenuItem", "file_type": "code", "source_file": null, "source_location": null}, {"id": "ui_profile_tab_build", "label": "build", "file_type": "code", "source_file": "features/profile_tab/ui/profile_tab.dart", "source_location": null}, {"id": "ui_profile_tab_buildhero", "label": "_buildHero", "file_type": "code", "source_file": "features/profile_tab/ui/profile_tab.dart", "source_location": null}, {"id": "ui_profile_tab_buildlevelcard", "label": "_buildLevelCard", "file_type": "code", "source_file": "features/profile_tab/ui/profile_tab.dart", "source_location": null}, {"id": "ui_profile_tab_buildcareerstats", "label": "_buildCareerStats", "file_type": "code", "source_file": "features/profile_tab/ui/profile_tab.dart", "source_location": null}, {"id": "ui_profile_tab_buildachievementssection", "label": "_buildAchievementsSection", "file_type": "code", "source_file": "features/profile_tab/ui/profile_tab.dart", "source_location": null}, {"id": "ui_profile_tab_showbadgeinfo", "label": "_showBadgeInfo", "file_type": "code", "source_file": "features/profile_tab/ui/profile_tab.dart", "source_location": null}, {"id": "ui_profile_tab_buildmenusection", "label": "_buildMenuSection", "file_type": "code", "source_file": "features/profile_tab/ui/profile_tab.dart", "source_location": null}, {"id": "ui_profile_tab_initials", "label": "_initials", "file_type": "code", "source_file": "features/profile_tab/ui/profile_tab.dart", "source_location": null}, {"id": "package_flutter_material_dart", "label": "package:flutter/material.dart", "file_type": "code", "source_file": null, "source_location": null}, {"id": "package_flutter_screenutil_flutter_screenutil_dart", "label": "package:flutter_screenutil/flutter_screenutil.dart", "file_type": "code", "source_file": null, "source_location": null}, {"id": "package_get_get_dart", "label": "package:get/get.dart", "file_type": "code", "source_file": null, "source_location": null}, {"id": "package_spanx_core_const_app_fonts_dart", "label": "package:spanx/core/const/app_fonts.dart", "file_type": "code", "source_file": null, "source_location": null}, {"id": "package_spanx_core_global_widgets_app_network_image_dart", "label": "package:spanx/core/global_widgets/app_network_image.dart", "file_type": "code", "source_file": null, "source_location": null}, {"id": "package_spanx_features_achievements_achievements_controller_dart", "label": "package:spanx/features/achievements/achievements_controller.dart", "file_type": "code", "source_file": null, "source_location": null}, {"id": "core_user_info_user_info_controller_dart", "label": "../../../core/user_info/user_info_controller.dart", "file_type": "code", "source_file": null, "source_location": null}, {"id": "controller_profile_tab_controller_dart", "label": "../controller/profile_tab_controller.dart", "file_type": "code", "source_file": null, "source_location": null}, {"id": "userinfocontroller", "label": "UserInfoController", "file_type": "code", "source_file": null, "source_location": null}, {"id": "achievementscontroller", "label": "AchievementsController", "file_type": "code", "source_file": null, "source_location": null}], "edges": [{"source": "c_users_vjtyl_downloads_spanx_extracted_spanx_lib_features_profile_tab_ui_profile_tab_dart", "target": "ui_profile_tab_profiletabpage", "relation": "defines", "confidence": "EXTRACTED", "confidence_score": 1.0, "source_file": "features/profile_tab/ui/profile_tab.dart", "source_location": null, "weight": 1.0}, {"source": "ui_profile_tab_profiletabpage", "target": "statelesswidget", "relation": "inherits", "confidence": "EXTRACTED", "confidence_score": 1.0, "source_file": "features/profile_tab/ui/profile_tab.dart", "source_location": null, "weight": 1.0}, {"source": "c_users_vjtyl_downloads_spanx_extracted_spanx_lib_features_profile_tab_ui_profile_tab_dart", "target": "ui_profile_tab_herostat", "relation": "defines", "confidence": "EXTRACTED", "confidence_score": 1.0, "source_file": "features/profile_tab/ui/profile_tab.dart", "source_location": null, "weight": 1.0}, {"source": "ui_profile_tab_herostat", "target": "statelesswidget", "relation": "inherits", "confidence": "EXTRACTED", "confidence_score": 1.0, "source_file": "features/profile_tab/ui/profile_tab.dart", "source_location": null, "weight": 1.0}, {"source": "c_users_vjtyl_downloads_spanx_extracted_spanx_lib_features_profile_tab_ui_profile_tab_dart", "target": "ui_profile_tab_statchip", "relation": "defines", "confidence": "EXTRACTED", "confidence_score": 1.0, "source_file": "features/profile_tab/ui/profile_tab.dart", "source_location": null, "weight": 1.0}, {"source": "ui_profile_tab_statchip", "target": "statelesswidget", "relation": "inherits", "confidence": "EXTRACTED", "confidence_score": 1.0, "source_file": "features/profile_tab/ui/profile_tab.dart", "source_location": null, "weight": 1.0}, {"source": "c_users_vjtyl_downloads_spanx_extracted_spanx_lib_features_profile_tab_ui_profile_tab_dart", "target": "ui_profile_tab_menuitem", "relation": "defines", "confidence": "EXTRACTED", "confidence_score": 1.0, "source_file": "features/profile_tab/ui/profile_tab.dart", "source_location": null, "weight": 1.0}, {"source": "ui_profile_tab_menuitem", "target": "statelesswidget", "relation": "inherits", "confidence": "EXTRACTED", "confidence_score": 1.0, "source_file": "features/profile_tab/ui/profile_tab.dart", "source_location": null, "weight": 1.0}, {"source": "c_users_vjtyl_downloads_spanx_extracted_spanx_lib_features_profile_tab_ui_profile_tab_dart", "target": "ui_profile_tab_kred", "relation": "defines", "confidence": "EXTRACTED", "confidence_score": 1.0, "source_file": "features/profile_tab/ui/profile_tab.dart", "source_location": null, "weight": 1.0}, {"source": "c_users_vjtyl_downloads_spanx_extracted_spanx_lib_features_profile_tab_ui_profile_tab_dart", "target": "ui_profile_tab_kreddk", "relation": "defines", "confidence": "EXTRACTED", "confidence_score": 1.0, "source_file": "features/profile_tab/ui/profile_tab.dart", "source_location": null, "weight": 1.0}, {"source": "c_users_vjtyl_downloads_spanx_extracted_spanx_lib_features_profile_tab_ui_profile_tab_dart", "target": "ui_profile_tab_kbg", "relation": "defines", "confidence": "EXTRACTED", "confidence_score": 1.0, "source_file": "features/profile_tab/ui/profile_tab.dart", "source_location": null, "weight": 1.0}, {"source": "c_users_vjtyl_downloads_spanx_extracted_spanx_lib_features_profile_tab_ui_profile_tab_dart", "target": "ui_profile_tab_kcard", "relation": "defines", "confidence": "EXTRACTED", "confidence_score": 1.0, "source_file": "features/profile_tab/ui/profile_tab.dart", "source_location": null, "weight": 1.0}, {"source": "c_users_vjtyl_downloads_spanx_extracted_spanx_lib_features_profile_tab_ui_profile_tab_dart", "target": "ui_profile_tab_ktext", "relation": "defines", "confidence": "EXTRACTED", "confidence_score": 1.0, "source_file": "features/profile_tab/ui/profile_tab.dart", "source_location": null, "weight": 1.0}, {"source": "c_users_vjtyl_downloads_spanx_extracted_spanx_lib_features_profile_tab_ui_profile_tab_dart", "target": "ui_profile_tab_kmuted", "relation": "defines", "confidence": "EXTRACTED", "confidence_score": 1.0, "source_file": "features/profile_tab/ui/profile_tab.dart", "source_location": null, "weight": 1.0}, {"source": "c_users_vjtyl_downloads_spanx_extracted_spanx_lib_features_profile_tab_ui_profile_tab_dart", "target": "ui_profile_tab_controller", "relation": "defines", "confidence": "EXTRACTED", "confidence_score": 1.0, "source_file": "features/profile_tab/ui/profile_tab.dart", "source_location": null, "weight": 1.0}, {"source": "c_users_vjtyl_downloads_spanx_extracted_spanx_lib_features_profile_tab_ui_profile_tab_dart", "target": "ui_profile_tab_userinfo", "relation": "defines", "confidence": "EXTRACTED", "confidence_score": 1.0, "source_file": "features/profile_tab/ui/profile_tab.dart", "source_location": null, "weight": 1.0}, {"source": "c_users_vjtyl_downloads_spanx_extracted_spanx_lib_features_profile_tab_ui_profile_tab_dart", "target": "ui_profile_tab_achievements", "relation": "defines", "confidence": "EXTRACTED", "confidence_score": 1.0, "source_file": "features/profile_tab/ui/profile_tab.dart", "source_location": null, "weight": 1.0}, {"source": "c_users_vjtyl_downloads_spanx_extracted_spanx_lib_features_profile_tab_ui_profile_tab_dart", "target": "ui_profile_tab_count", "relation": "defines", "confidence": "EXTRACTED", "confidence_score": 1.0, "source_file": "features/profile_tab/ui/profile_tab.dart", "source_location": null, "weight": 1.0}, {"source": "c_users_vjtyl_downloads_spanx_extracted_spanx_lib_features_profile_tab_ui_profile_tab_dart", "target": "ui_profile_tab_label", "relation": "defines", "confidence": "EXTRACTED", "confidence_score": 1.0, "source_file": "features/profile_tab/ui/profile_tab.dart", "source_location": null, "weight": 1.0}, {"source": "c_users_vjtyl_downloads_spanx_extracted_spanx_lib_features_profile_tab_ui_profile_tab_dart", "target": "ui_profile_tab_icon", "relation": "defines", "confidence": "EXTRACTED", "confidence_score": 1.0, "source_file": "features/profile_tab/ui/profile_tab.dart", "source_location": null, "weight": 1.0}, {"source": "c_users_vjtyl_downloads_spanx_extracted_spanx_lib_features_profile_tab_ui_profile_tab_dart", "target": "icondata", "relation": "references", "confidence": "EXTRACTED", "confidence_score": 1.0, "source_file": "features/profile_tab/ui/profile_tab.dart", "source_location": null, "weight": 1.0, "context": "variable_type"}, {"source": "c_users_vjtyl_downloads_spanx_extracted_spanx_lib_features_profile_tab_ui_profile_tab_dart", "target": "ui_profile_tab_label", "relation": "defines", "confidence": "EXTRACTED", "confidence_score": 1.0, "source_file": "features/profile_tab/ui/profile_tab.dart", "source_location": null, "weight": 1.0}, {"source": "c_users_vjtyl_downloads_spanx_extracted_spanx_lib_features_profile_tab_ui_profile_tab_dart", "target": "ui_profile_tab_value", "relation": "defines", "confidence": "EXTRACTED", "confidence_score": 1.0, "source_file": "features/profile_tab/ui/profile_tab.dart", "source_location": null, "weight": 1.0}, {"source": "c_users_vjtyl_downloads_spanx_extracted_spanx_lib_features_profile_tab_ui_profile_tab_dart", "target": "ui_profile_tab_color", "relation": "defines", "confidence": "EXTRACTED", "confidence_score": 1.0, "source_file": "features/profile_tab/ui/profile_tab.dart", "source_location": null, "weight": 1.0}, {"source": "c_users_vjtyl_downloads_spanx_extracted_spanx_lib_features_profile_tab_ui_profile_tab_dart", "target": "color", "relation": "references", "confidence": "EXTRACTED", "confidence_score": 1.0, "source_file": "features/profile_tab/ui/profile_tab.dart", "source_location": null, "weight": 1.0, "context": "variable_type"}, {"source": "c_users_vjtyl_downloads_spanx_extracted_spanx_lib_features_profile_tab_ui_profile_tab_dart", "target": "ui_profile_tab_item", "relation": "defines", "confidence": "EXTRACTED", "confidence_score": 1.0, "source_file": "features/profile_tab/ui/profile_tab.dart", "source_location": null, "weight": 1.0}, {"source": "c_users_vjtyl_downloads_spanx_extracted_spanx_lib_features_profile_tab_ui_profile_tab_dart", "target": "profilemenuitem", "relation": "references", "confidence": "EXTRACTED", "confidence_score": 1.0, "source_file": "features/profile_tab/ui/profile_tab.dart", "source_location": null, "weight": 1.0, "context": "variable_type"}, {"source": "c_users_vjtyl_downloads_spanx_extracted_spanx_lib_features_profile_tab_ui_profile_tab_dart", "target": "ui_profile_tab_build", "relation": "defines", "confidence": "EXTRACTED", "confidence_score": 1.0, "source_file": "features/profile_tab/ui/profile_tab.dart", "source_location": null, "weight": 1.0}, {"source": "c_users_vjtyl_downloads_spanx_extracted_spanx_lib_features_profile_tab_ui_profile_tab_dart", "target": "ui_profile_tab_buildhero", "relation": "defines", "confidence": "EXTRACTED", "confidence_score": 1.0, "source_file": "features/profile_tab/ui/profile_tab.dart", "source_location": null, "weight": 1.0}, {"source": "c_users_vjtyl_downloads_spanx_extracted_spanx_lib_features_profile_tab_ui_profile_tab_dart", "target": "ui_profile_tab_buildlevelcard", "relation": "defines", "confidence": "EXTRACTED", "confidence_score": 1.0, "source_file": "features/profile_tab/ui/profile_tab.dart", "source_location": null, "weight": 1.0}, {"source": "c_users_vjtyl_downloads_spanx_extracted_spanx_lib_features_profile_tab_ui_profile_tab_dart", "target": "ui_profile_tab_buildcareerstats", "relation": "defines", "confidence": "EXTRACTED", "confidence_score": 1.0, "source_file": "features/profile_tab/ui/profile_tab.dart", "source_location": null, "weight": 1.0}, {"source": "c_users_vjtyl_downloads_spanx_extracted_spanx_lib_features_profile_tab_ui_profile_tab_dart", "target": "ui_profile_tab_buildachievementssection", "relation": "defines", "confidence": "EXTRACTED", "confidence_score": 1.0, "source_file": "features/profile_tab/ui/profile_tab.dart", "source_location": null, "weight": 1.0}, {"source": "c_users_vjtyl_downloads_spanx_extracted_spanx_lib_features_profile_tab_ui_profile_tab_dart", "target": "ui_profile_tab_showbadgeinfo", "relation": "defines", "confidence": "EXTRACTED", "confidence_score": 1.0, "source_file": "features/profile_tab/ui/profile_tab.dart", "source_location": null, "weight": 1.0}, {"source": "c_users_vjtyl_downloads_spanx_extracted_spanx_lib_features_profile_tab_ui_profile_tab_dart", "target": "ui_profile_tab_buildmenusection", "relation": "defines", "confidence": "EXTRACTED", "confidence_score": 1.0, "source_file": "features/profile_tab/ui/profile_tab.dart", "source_location": null, "weight": 1.0}, {"source": "c_users_vjtyl_downloads_spanx_extracted_spanx_lib_features_profile_tab_ui_profile_tab_dart", "target": "ui_profile_tab_initials", "relation": "defines", "confidence": "EXTRACTED", "confidence_score": 1.0, "source_file": "features/profile_tab/ui/profile_tab.dart", "source_location": null, "weight": 1.0}, {"source": "c_users_vjtyl_downloads_spanx_extracted_spanx_lib_features_profile_tab_ui_profile_tab_dart", "target": "ui_profile_tab_herostat", "relation": "defines", "confidence": "EXTRACTED", "confidence_score": 1.0, "source_file": "features/profile_tab/ui/profile_tab.dart", "source_location": null, "weight": 1.0}, {"source": "c_users_vjtyl_downloads_spanx_extracted_spanx_lib_features_profile_tab_ui_profile_tab_dart", "target": "ui_profile_tab_build", "relation": "defines", "confidence": "EXTRACTED", "confidence_score": 1.0, "source_file": "features/profile_tab/ui/profile_tab.dart", "source_location": null, "weight": 1.0}, {"source": "c_users_vjtyl_downloads_spanx_extracted_spanx_lib_features_profile_tab_ui_profile_tab_dart", "target": "ui_profile_tab_statchip", "relation": "defines", "confidence": "EXTRACTED", "confidence_score": 1.0, "source_file": "features/profile_tab/ui/profile_tab.dart", "source_location": null, "weight": 1.0}, {"source": "c_users_vjtyl_downloads_spanx_extracted_spanx_lib_features_profile_tab_ui_profile_tab_dart", "target": "ui_profile_tab_build", "relation": "defines", "confidence": "EXTRACTED", "confidence_score": 1.0, "source_file": "features/profile_tab/ui/profile_tab.dart", "source_location": null, "weight": 1.0}, {"source": "c_users_vjtyl_downloads_spanx_extracted_spanx_lib_features_profile_tab_ui_profile_tab_dart", "target": "ui_profile_tab_menuitem", "relation": "defines", "confidence": "EXTRACTED", "confidence_score": 1.0, "source_file": "features/profile_tab/ui/profile_tab.dart", "source_location": null, "weight": 1.0}, {"source": "c_users_vjtyl_downloads_spanx_extracted_spanx_lib_features_profile_tab_ui_profile_tab_dart", "target": "ui_profile_tab_build", "relation": "defines", "confidence": "EXTRACTED", "confidence_score": 1.0, "source_file": "features/profile_tab/ui/profile_tab.dart", "source_location": null, "weight": 1.0}, {"source": "c_users_vjtyl_downloads_spanx_extracted_spanx_lib_features_profile_tab_ui_profile_tab_dart", "target": "package_flutter_material_dart", "relation": "imports", "confidence": "EXTRACTED", "confidence_score": 1.0, "source_file": "features/profile_tab/ui/profile_tab.dart", "source_location": null, "weight": 1.0}, {"source": "c_users_vjtyl_downloads_spanx_extracted_spanx_lib_features_profile_tab_ui_profile_tab_dart", "target": "package_flutter_screenutil_flutter_screenutil_dart", "relation": "imports", "confidence": "EXTRACTED", "confidence_score": 1.0, "source_file": "features/profile_tab/ui/profile_tab.dart", "source_location": null, "weight": 1.0}, {"source": "c_users_vjtyl_downloads_spanx_extracted_spanx_lib_features_profile_tab_ui_profile_tab_dart", "target": "package_get_get_dart", "relation": "imports", "confidence": "EXTRACTED", "confidence_score": 1.0, "source_file": "features/profile_tab/ui/profile_tab.dart", "source_location": null, "weight": 1.0}, {"source": "c_users_vjtyl_downloads_spanx_extracted_spanx_lib_features_profile_tab_ui_profile_tab_dart", "target": "package_spanx_core_const_app_fonts_dart", "relation": "imports", "confidence": "EXTRACTED", "confidence_score": 1.0, "source_file": "features/profile_tab/ui/profile_tab.dart", "source_location": null, "weight": 1.0}, {"source": "c_users_vjtyl_downloads_spanx_extracted_spanx_lib_features_profile_tab_ui_profile_tab_dart", "target": "package_spanx_core_global_widgets_app_network_image_dart", "relation": "imports", "confidence": "EXTRACTED", "confidence_score": 1.0, "source_file": "features/profile_tab/ui/profile_tab.dart", "source_location": null, "weight": 1.0}, {"source": "c_users_vjtyl_downloads_spanx_extracted_spanx_lib_features_profile_tab_ui_profile_tab_dart", "target": "package_spanx_features_achievements_achievements_controller_dart", "relation": "imports", "confidence": "EXTRACTED", "confidence_score": 1.0, "source_file": "features/profile_tab/ui/profile_tab.dart", "source_location": null, "weight": 1.0}, {"source": "c_users_vjtyl_downloads_spanx_extracted_spanx_lib_features_profile_tab_ui_profile_tab_dart", "target": "core_user_info_user_info_controller_dart", "relation": "imports", "confidence": "EXTRACTED", "confidence_score": 1.0, "source_file": "features/profile_tab/ui/profile_tab.dart", "source_location": null, "weight": 1.0}, {"source": "c_users_vjtyl_downloads_spanx_extracted_spanx_lib_features_profile_tab_ui_profile_tab_dart", "target": "controller_profile_tab_controller_dart", "relation": "imports", "confidence": "EXTRACTED", "confidence_score": 1.0, "source_file": "features/profile_tab/ui/profile_tab.dart", "source_location": null, "weight": 1.0}, {"source": "c_users_vjtyl_downloads_spanx_extracted_spanx_lib_features_profile_tab_ui_profile_tab_dart", "target": "userinfocontroller", "relation": "references", "confidence": "EXTRACTED", "confidence_score": 1.0, "source_file": "features/profile_tab/ui/profile_tab.dart", "source_location": null, "weight": 1.0, "context": "type_lookup"}, {"source": "c_users_vjtyl_downloads_spanx_extracted_spanx_lib_features_profile_tab_ui_profile_tab_dart", "target": "achievementscontroller", "relation": "references", "confidence": "EXTRACTED", "confidence_score": 1.0, "source_file": "features/profile_tab/ui/profile_tab.dart", "source_location": null, "weight": 1.0, "context": "type_lookup"}, {"source": "c_users_vjtyl_downloads_spanx_extracted_spanx_lib_features_profile_tab_ui_profile_tab_dart", "target": "color", "relation": "references", "confidence": "EXTRACTED", "confidence_score": 1.0, "source_file": "features/profile_tab/ui/profile_tab.dart", "source_location": null, "weight": 1.0, "context": "type_lookup"}]}